smc/__init__.py
smc/__version__.py
smc/compat.py
smc/actions/__init__.py
smc/actions/_search.py
smc/actions/cert_extract.py
smc/actions/ozinga.py
smc/actions/parse.py
smc/actions/test.py
smc/actions/test_graphql.py
smc/administration/__init__.py
smc/administration/access_rights.py
smc/administration/license.py
smc/administration/reports.py
smc/administration/role.py
smc/administration/scheduled_tasks.py
smc/administration/system.py
smc/administration/tasks.py
smc/administration/updates.py
smc/administration/certificates/__init__.py
smc/administration/certificates/tls.py
smc/administration/certificates/tls_common.py
smc/administration/certificates/vpn.py
smc/administration/user_auth/__init__.py
smc/administration/user_auth/servers.py
smc/administration/user_auth/users.py
smc/api/__init__.py
smc/api/common.py
smc/api/configloader.py
smc/api/entry_point.py
smc/api/exceptions.py
smc/api/session.py
smc/api/web.py
smc/base/__init__.py
smc/base/collection.py
smc/base/decorators.py
smc/base/mixins.py
smc/base/model.py
smc/base/structs.py
smc/base/transaction.py
smc/base/util.py
smc/core/__init__.py
smc/core/addon.py
smc/core/collection.py
smc/core/contact_address.py
smc/core/engine.py
smc/core/engine_vss.py
smc/core/engines.py
smc/core/general.py
smc/core/interfaces.py
smc/core/name_cache.py
smc/core/node.py
smc/core/resource.py
smc/core/route.py
smc/core/sub_interfaces.py
smc/core/waiters.py
smc/elements/__init__.py
smc/elements/group.py
smc/elements/helpers.py
smc/elements/netlink.py
smc/elements/network.py
smc/elements/other.py
smc/elements/profiles.py
smc/elements/protocols.py
smc/elements/servers.py
smc/elements/service.py
smc/elements/situations.py
smc/elements/user.py
smc/policy/__init__.py
smc/policy/file_filtering.py
smc/policy/interface.py
smc/policy/ips.py
smc/policy/layer2.py
smc/policy/layer3.py
smc/policy/policy.py
smc/policy/qos.py
smc/policy/rule.py
smc/policy/rule_elements.py
smc_python-0.6.2.dist-info/DESCRIPTION.rst
smc_python-0.6.2.dist-info/METADATA
smc_python-0.6.2.dist-info/RECORD
smc_python-0.6.2.dist-info/WHEEL
smc_python-0.6.2.dist-info/metadata.json
smc_python-0.6.2.dist-info/top_level.txt
