Metadata-Version: 2.0
Name: smc-python
Version: 0.6.2
Summary: Python based API to Stonesoft Security Management Center
Home-page: http://github.com/gabstopper/smc-python
Author: David LePage
Author-email: dwlepage70@gmail.com
License: Apache 2.0
Platform: UNKNOWN
Classifier: Development Status :: 5 - Production/Stable
Classifier: Programming Language :: Python
Classifier: Programming Language :: Python :: 2.7
Classifier: Programming Language :: Python :: 3.4
Classifier: Programming Language :: Python :: 3.5
Classifier: Programming Language :: Python :: 3
Classifier: License :: OSI Approved :: Apache Software License
Requires-Dist: requests (>=2.12.0)
